MANIFEST.in
README.rst
setup.py
src/ua2/__init__.py
src/ua2.carbon.egg-info/PKG-INFO
src/ua2.carbon.egg-info/SOURCES.txt
src/ua2.carbon.egg-info/dependency_links.txt
src/ua2.carbon.egg-info/eager_resources.txt
src/ua2.carbon.egg-info/namespace_packages.txt
src/ua2.carbon.egg-info/not-zip-safe
src/ua2.carbon.egg-info/top_level.txt
src/ua2/carbon/__init__.py
src/ua2/carbon/conf.py
src/ua2/carbon/decorators.py
src/ua2/carbon/loaders.py
src/ua2/carbon/measure.py
src/ua2/carbon/middleware.py
src/ua2/carbon/profile.py
src/ua2/carbon/stream.py