Metadata-Version: 1.0
Name: ua2.carbon
Version: 0.0.3
Summary: Tool for stream statistics to carbon daemon (from graphite)
Home-page: https://bitbucket.org/ua2crm/ua2.carbon
Author: Vic
Author-email: vic@ua2web.com
License: BSD License
Platform: UNKNOWN
